conversortemperatura/__init__.py
conversortemperatura/conversor.py
conversortemperatura-1.0.dist-info/WHEEL
conversortemperatura-1.0.dist-info/METADATA
conversortemperatura-1.0.dist-info/RECORD
